[
	{
		"academy":"钒钛学院",
		"majors":["材料科学与工程","材料成型及控制工程","新能源材料与器件","新能源科学与工程","采矿工程","冶金工程"]
	},
	{
		"academy":"康养学院",
		"majors":["护理学","健康与服务与管理","护理","康复治疗技术","康复治疗学"]
	},
	{
		"academy":"生物与化学工程学院",
		"majors":["化学工程与工艺专业","环境工程","生物工程","园艺"]
	},
	{
		"academy":"基础医学院",
		"majors":["临床医学","眼视光技术"]
	},
	{
		"academy":"土木与建筑工程学院",
		"majors":["工程管理","建筑学","测绘工程","城乡规划","智能建造","土木工程"]
	},
	{
		"academy":"数学与计算机学院",
		"majors":["软件工程","计算机科学与技术","网络工程","数据科学与大数据技术","信息与计算科学"]
	},
	{
		"academy":"智能制造学院",
		"majors":["车辆工程","机器人工程","机械电子工程","机械设计制造及其自动化"]
	},
	{
		"academy":"电气信息工程学院",
		"majors":["自动化","电子信息工程","电气工程及其自动化"]
	},
	{
		"academy":"经济与管理学院",
		"majors":["国际经济与贸易","大数据管理与应用","物流管理","财务管理","工商管理","会计学"]
	},
	{
		"academy":"文学院",
		"majors":["汉语言文学","秘书学","学前教育"]
	},
	{
		"academy":"法学院",
		"majors":["法学","行政管理","旅游管理"]
	},
	{
		"academy":"艺术学院",
		"majors":["环境设计","产品设计","服装与服饰设计","数字媒体艺术","工艺美术","雕刻艺术设计","视觉传达设计"]
	},
	{
		"academy":"外国语学院",
		"majors":["英语专业","商务英语专业","翻译专业"]
	}
]
